llama_index/llms/llama_cpp/__init__.py
llama_index/llms/llama_cpp/base.py
llama_index/llms/llama_cpp/llama_utils.py
llama_index_llms_llama_cpp-0.5.1.dist-info/METADATA
llama_index_llms_llama_cpp-0.5.1.dist-info/WHEEL
llama_index_llms_llama_cpp-0.5.1.dist-info/licenses/LICENSE
llama_index_llms_llama_cpp-0.5.1.dist-info/RECORD
